datalayer_pycrdt-0.12.17.dist-info/METADATA
datalayer_pycrdt-0.12.17.dist-info/WHEEL
datalayer_pycrdt-0.12.17.dist-info/licenses/LICENSE
pycrdt/__init__.py
pycrdt/_array.py
pycrdt/_awareness.py
pycrdt/_base.py
pycrdt/_doc.py
pycrdt/_map.py
pycrdt/_provider.py
pycrdt/_pycrdt.pyi
pycrdt/_pycrdt.pypy310-pp73-s390x-linux-gnu.so
pycrdt/_sync.py
pycrdt/_text.py
pycrdt/_transaction.py
pycrdt/_undo.py
pycrdt/_update.py
pycrdt/_version.py
pycrdt/_xml.py
pycrdt/py.typed
datalayer_pycrdt-0.12.17.dist-info/RECORD
